PEER_pytorch/ChunkedPEER.py
PEER_pytorch/PEER.py
PEER_pytorch/PEERLora.py
PEER_pytorch/PK.py
PEER_pytorch/PKAttention.py
PEER_pytorch/__init__.py
peer_pytorch-0.2.1.dist-info/METADATA
peer_pytorch-0.2.1.dist-info/WHEEL
peer_pytorch-0.2.1.dist-info/licenses/LICENSE
peer_pytorch-0.2.1.dist-info/RECORD
