Metadata-Version: 2.3
Name: PEER-pytorch
Version: 0.2.1
Summary: PEER - Pytorch
Project-URL: Homepage, https://pypi.org/project/PEER-pytorch/
Project-URL: Repository, https://github.com/lucidrains/PEER-pytorch
Author-email: Phil Wang <lucidrains@gmail.com>
License: MIT License
License-File: LICENSE
Keywords: artificial intelligence,deep learning,mixture of experts,product key
Classifier: Development Status :: 4 - Beta
Classifier: Intended Audience :: Developers
Classifier: License :: OSI Approved :: MIT License
Classifier: Programming Language :: Python :: 3.8
Classifier: Topic :: Scientific/Engineering :: Artificial Intelligence
Requires-Python: >=3.8
Requires-Dist: einops>=0.8.0
Requires-Dist: einx>=0.3.0
Requires-Dist: torch>=2.0
